notemodule/__init__.py
notemodule/notemodule.py
notemodule-0.1.4.dist-info/LICENSE
notemodule-0.1.4.dist-info/METADATA
notemodule-0.1.4.dist-info/WHEEL
notemodule-0.1.4.dist-info/top_level.txt
notemodule-0.1.4.dist-info/RECORD
