Metadata-Version: 2.1
Name: notemodule
Version: 0.1.4
Summary: Convert Jupyter notebooks to python modules (and import them into your code)
Author-email: Atur Sams <atursams@gmail.com>
License: MIT
License-File: LICENSE
Requires-Dist: nbformat
